{"type":"registration-form","name":"Registration Form","data":{"3":{"data":[{"col":"1","desc":"First Name","editable":"true","id":"fadb53ab-60e5-438b-8908-d45cc5638d48","label":"First Name","match":"","maxlength":"30","req":"true","row":"1","sizex":"12","sizey":"1","title":"Text Field","type":"text-field","validation":"name","panel":"3"},{"col":"1","desc":"official rules","editable":"true","id":"c98330c7-c167-487b-9630-046577c6baf3","label":"<a href=\"http://dja.com\" target=\"_blank\" rel=\"nofollow\">official rules</a>","prechecked":"false","req":"false","row":"2","sizex":"12","sizey":"1","title":"Checkbox","type":"checkbox","panel":"3"}],"bypass-user-completed-form":"","bypass-user-entry-limit":"","bypass-user-entry-limit-identifier":"session-and-uid","bypass-user-ineligible":"","bypass-user-ineligible-identifier":"session","save-data-from":"entire-page","submit-action":"save-and-submit","submit-next-page":""}},"hasFormElement":true,"hasFormElementArray":["3"],"variables":{}}